pentest_ai/__init__.py
pentest_ai/core.py
pentest_ai-0.1.2.dist-info/METADATA
pentest_ai-0.1.2.dist-info/WHEEL
pentest_ai-0.1.2.dist-info/entry_points.txt
pentest_ai-0.1.2.dist-info/top_level.txt
pentest_ai-0.1.2.dist-info/RECORD
