Metadata-Version: 2.2
Name: pentest-ai
Version: 0.1.2
Summary: An AI-powered pentesting tool
Home-page: https://github.com/IMApurbo/pentest-ai
Author: AKM Korishee Apurbo
Author-email: bandinvisible8@gmail.com
License: MIT
Classifier: Programming Language :: Python :: 3
Classifier: License :: OSI Approved :: MIT License
Classifier: Operating System :: OS Independent
Requires-Python: >=3.7
Requires-Dist: groq>=0.4.0
Requires-Dist: colorama>=0.4.6
Requires-Dist: pyfiglet>=0.8.post1
Requires-Dist: rich>=13.7.1
Dynamic: author
Dynamic: author-email
Dynamic: classifier
Dynamic: description
Dynamic: description-content-type
Dynamic: home-page
Dynamic: license
Dynamic: requires-dist
Dynamic: requires-python
Dynamic: summary
